map/__init__.py
map/base.py
map/folium_map.py
map/geojson.py
map/shape.py
map/util.py
map/utilities.py
map_mapilio-0.0.34.dist-info/METADATA
map_mapilio-0.0.34.dist-info/WHEEL
map_mapilio-0.0.34.dist-info/top_level.txt
map_mapilio-0.0.34.dist-info/RECORD
