Metadata-Version: 2.1
Name: map-mapilio
Version: 0.0.34
Summary: Mapilio Map Library
Home-page: https://github.com/mapilio/helper.git
Author: Mapilio - Ozcan Durak & M.Can VARER
Author-email: ozcan@visiosoft.com.tr
License: MIT
Project-URL: Bug Reports, https://github.com/mapilio/map/issues
Project-URL: Say Thanks!, https://mapilio.com/#contact
Project-URL: Source, https://github.com/mapilio/map/
Requires-Python: >=3.6, <4
Requires-Dist: folium
Requires-Dist: requests
Requires-Dist: pillow
Requires-Dist: urllib3
Requires-Dist: addict
